rhetoric/util.py
rhetoric/compat.py
rhetoric/__init__.py
rhetoric/view.py
rhetoric/middleware.py
rhetoric/request.py
rhetoric/url.py
rhetoric/registry.py
rhetoric/exceptions.py
rhetoric/path.py
rhetoric/adt.py
rhetoric/config/routes.py
rhetoric/config/predicates.py
rhetoric/config/util.py
rhetoric/config/__init__.py
rhetoric/config/rendering.py
rhetoric/config/views.py
rhetoric/config/adt.py
Rhetoric-0.2.3.dist-info/DESCRIPTION.rst
Rhetoric-0.2.3.dist-info/WHEEL
Rhetoric-0.2.3.dist-info/RECORD
Rhetoric-0.2.3.dist-info/top_level.txt
Rhetoric-0.2.3.dist-info/METADATA
Rhetoric-0.2.3.dist-info/metadata.json
tests/blogs/forms_test.py
tests/blogs/__init__.py
tests/testapp/__init__.py
tests/testapp/manage.py
tests/testapp/testapp/settings.py
tests/testapp/testapp/wsgi.py
tests/testapp/testapp/__init__.py
tests/testapp/testapp/urls.py
tests/testapp/testapp/types.py
tests/testapp/testapp/rhetoric_config.py
tests/testapp/testapp/articles/__init__.py
tests/testapp/testapp/articles/forms.py
tests/testapp/testapp/articles/views.py
tests/testapp/testapp/articles/models.py
tests/testapp/testapp/trading/__init__.py
tests/testapp/testapp/trading/logic.py
tests/testapp/testapp/trading/models.py
tests/testapp/testapp/blog/__init__.py
tests/testapp/testapp/blog/forms.py
tests/testapp/testapp/blog/views.py
tests/testapp/testapp/index/__init__.py
tests/testapp/testapp/index/views.py
tests/config/__init__.py
tests/config/config_tests.py
