Metadata-Version: 2.0
Name: Rhetoric
Version: 0.2.3
Summary: Pyramid-like routes for Django projects
Home-page: https://github.com/avanov/Rhetoric
Author: Maxim Avanov
Author-email: maxim.avanov@gmail.com
License: MIT
Download-URL: https://github.com/avanov/Rhetoric
Keywords: pyramid django routes
Platform: UNKNOWN
Classifier: Development Status :: 4 - Beta
Classifier: Environment :: Web Environment
Classifier: Framework :: Django
Classifier: Intended Audience :: Developers
Classifier: License :: OSI Approved
Classifier: License :: OSI Approved :: MIT License
Classifier: Operating System :: MacOS
Classifier: Operating System :: Microsoft
Classifier: Operating System :: POSIX
Classifier: Programming Language :: Python
Classifier: Programming Language :: Python :: 2.7
Classifier: Programming Language :: Python :: 3.3
Classifier: Programming Language :: Python :: 3.4
Classifier: Topic :: Internet :: WWW/HTTP
Classifier: Topic :: Internet :: WWW/HTTP :: Dynamic Content
Classifier: Topic :: Internet :: WWW/HTTP :: WSGI :: Middleware
Classifier: Topic :: Software Development :: Libraries :: Python Modules
Classifier: Topic :: Software Development :: Libraries :: Application Frameworks
Requires-Dist: Django (>=1.4)
Requires-Dist: venusian (>=1.0)
Requires-Dist: six
